shippy/__init__.py
shippy/api.py
shippy/gateway.py
shippy/shipment.py
shippy-0.1.dist-info/METADATA
shippy-0.1.dist-info/WHEEL
shippy-0.1.dist-info/entry_points.txt
shippy-0.1.dist-info/top_level.txt
shippy-0.1.dist-info/zip-safe
shippy-0.1.dist-info/RECORD
